pdf2test/__init__.py
pdf2test/pdf2test.py
tests/__init__.py
pdf2test-0.1.1.dist-info/LICENSE
pdf2test-0.1.1.dist-info/METADATA
pdf2test-0.1.1.dist-info/WHEEL
pdf2test-0.1.1.dist-info/top_level.txt
pdf2test-0.1.1.dist-info/RECORD
